bitwarden_exporter/__init__.py
bitwarden_exporter/__main__.py
bitwarden_exporter/bw_models.py
bitwarden_exporter/cli.py
bitwarden_exporter/keepass.py
bitwarden_exporter/settings.py
bitwarden_exporter-1.7.0.dist-info/WHEEL
bitwarden_exporter-1.7.0.dist-info/entry_points.txt
bitwarden_exporter-1.7.0.dist-info/METADATA
bitwarden_exporter-1.7.0.dist-info/RECORD
