Metadata-Version: 2.4
Name: bitwarden-exporter
Version: 1.7.0
Summary: Export Bitwarden vault
Keywords: bitwarden,export,keepass,backup
Author: arpan
Author-email: arpan <me@arpanrec.com>
License-Expression: MIT
Classifier: Development Status :: 5 - Production/Stable
Classifier: Intended Audience :: End Users/Desktop
Classifier: Operating System :: Unix
Classifier: Operating System :: POSIX
Classifier: Operating System :: Microsoft :: Windows
Classifier: License :: OSI Approved :: MIT License
Classifier: Programming Language :: Python
Classifier: Programming Language :: Python :: 3.10
Classifier: Programming Language :: Python :: 3.11
Classifier: Programming Language :: Python :: 3.12
Classifier: Programming Language :: Python :: 3.13
Classifier: Programming Language :: Python :: Implementation :: PyPy
Classifier: Topic :: Utilities
Classifier: Topic :: System :: Archiving
Classifier: Topic :: System :: Archiving :: Backup
Classifier: Topic :: Security
Classifier: Topic :: Security :: Cryptography
Classifier: Topic :: System :: Recovery Tools
Requires-Dist: gnupg==2.3.1
Requires-Dist: pydantic==2.12.3
Requires-Dist: pykeepass==4.1.1.post1
Requires-Dist: cachier==4.1.0
Requires-Dist: pyfiglet==1.0.4
Requires-Dist: jmespath>=1.0.1
Requires-Dist: bandit==1.8.6 ; extra == 'dev'
Requires-Dist: black==25.9.0 ; extra == 'dev'
Requires-Dist: isort==7.0.0 ; extra == 'dev'
Requires-Dist: mypy==1.18.2 ; extra == 'dev'
Requires-Dist: neovim==0.3.1 ; extra == 'dev'
Requires-Dist: pylint==4.0.2 ; extra == 'dev'
Requires-Dist: pyright==1.1.406 ; extra == 'dev'
Requires-Dist: types-pyyaml==6.0.12.20250915 ; extra == 'dev'
Requires-Dist: types-requests==2.32.4.20250913 ; extra == 'dev'
Requires-Dist: types-jmespath==1.0.2.20250809 ; extra == 'dev'
Requires-Python: >=3.10
Provides-Extra: dev
